unichat_mcp_server/__init__.py
unichat_mcp_server/server.py
iflow_mcp_unichat_mcp_server-0.2.20.dist-info/METADATA
iflow_mcp_unichat_mcp_server-0.2.20.dist-info/WHEEL
iflow_mcp_unichat_mcp_server-0.2.20.dist-info/entry_points.txt
iflow_mcp_unichat_mcp_server-0.2.20.dist-info/licenses/LICENSE
iflow_mcp_unichat_mcp_server-0.2.20.dist-info/RECORD
