Metadata-Version: 2.4
Name: iflow-mcp_unichat-mcp-server
Version: 0.2.20
Summary: Unichat MCP Server
Author-email: Stefan <shear.0-corned@icloud.com>
License-File: LICENSE
Requires-Python: >=3.11
Requires-Dist: mcp>=1.0.0
Requires-Dist: unichat>=4.1.30
